Metadata-Version: 2.1
Name: colorprynt
Version: 0.1.0
Summary: Print color text easily.
Home-page: UNKNOWN
Author: Jaedson Silva
Author-email: imunknowuser@protonmail.com
License: MIT
Project-URL: Source code, https://github.com/jaedsonpys/colorprynt
Platform: UNKNOWN
